{"title":"springBoot-Study-day01","uid":"48f7fbdaf0e0dd4f6b63c39c2a27cf68","slug":"springBoot/springBoot-Study-day01","date":"2022-11-11T08:23:35.000Z","updated":"2022-11-13T10:49:11.577Z","comments":true,"path":"api/articles/springBoot/springBoot-Study-day01.json","keywords":null,"cover":"/img/springBoot.jpg","content":"<p>先去学习Maven了, 真的和多米诺骨牌一样, 发现自己球也不懂.</p>\n<hr>\n<p>学完Maven和Spring的IOC了, 今天开始学习springBoot</p>\n<p>springBoot是用来快速启动spring了, 解决了spring xml配置的繁琐和包文件的导入麻烦问题. </p>\n<div class=\"custom-quote tip\">\n<span class=\"custom-quote-svg\"><svg width=\"24\" height=\"24\" viewBox=\"0 0 24 24\" fill=\"\" xmlns=\"http://www.w3.org/2000/svg\" data-reactroot=\"\">\n<path fill=\"\" d=\"M20.86 14.13C20 14.7 19.56 15.74 19.77 16.76C20.13 18.55 18.55 20.13 16.76 19.77C15.74 19.57 14.7 20 14.13 20.86C13.12 22.38 10.89 22.38 9.88 20.86C9.3 20 8.26 19.56 7.24 19.77C5.45 20.13 3.87 18.55 4.23 16.76C4.43 15.74 4 14.7 3.14 14.13C1.62 13.12 1.62 10.89 3.14 9.88C4 9.3 4.44 8.26 4.23 7.24C3.87 5.45 5.45 3.87 7.24 4.23C8.26 4.44 9.3 4 9.87 3.14C10.88 1.62 13.11 1.62 14.12 3.14C14.7 4 15.74 4.44 16.76 4.23C18.55 3.87 20.13 5.45 19.77 7.24C19.56 8.26 20 9.3 20.86 9.87C22.38 10.88 22.38 13.12 20.86 14.13Z\" undefined=\"1\"></path>\n<path stroke-linejoin=\"round\" stroke-linecap=\"round\" stroke-miterlimit=\"10\" stroke-width=\"2\" stroke=\"\" d=\"M12.01 15C12.01 14.5 12.01 14.5 12.01 14.5C12.04 13.75 13 13.46 14.04 12.2C14.41 11.74 14.69 11.41 14.86 10.85C15.15 9.95 14.92 9.18 14.86 9.02C14.8 8.79 14.52 8 13.72 7.46C13.06 7.02 12.42 7 12.14 7C11.9 7 11.36 7 10.78 7.3C10.28 7.56 9.98 7.9 9.83 8.1C9.24 8.82 9.06 9.63 9 10.06\"></path>\n<path stroke-linecap=\"round\" stroke-miterlimit=\"10\" stroke-width=\"2\" stroke=\"\" d=\"M11.99 18H12.01\"></path>\n</svg></span>\n<p class=\"custom-quote-title\">提示</p>\n<p>SpringBoot不是对Spring的进一步强化, 而是对Spring的优化, 功能上没有多什么</p>\n\n</div>\n<p>好了, G了, 还是要学Spring</p>\n<p><a href=\"https://www.bilibili.com/video/BV1Fi4y1S7ix?p=1&spm_id_from=pageDriver&vd_source=79f488fa065eee08ba72fa4d2ffc9a26\">SSM框架-导学内容_哔哩哔哩_bilibili</a></p>\n<p>我心态崩了, 还要学tmd javaweb, javaweb又有三十四小时的课! 草了</p>\n","feature":true,"text":"先去学习Maven了, 真的和多米诺骨牌一样, 发现自己球也不懂. 学完Maven和Spring的IOC了, 今天开始学习springBoot springBoot是用来快速启动spring了, 解决了spring xml配置的繁琐和包文件的导入麻烦问题. 提示 SpringBo...","link":"","photos":[],"count_time":{"symbolsCount":280,"symbolsTime":"1 mins."},"categories":[{"name":"Study","slug":"Study","count":13,"path":"api/categories/Study.json"}],"tags":[{"name":"springBoot","slug":"springBoot","count":1,"path":"api/tags/springBoot.json"}],"toc":"","author":{"name":"Someone Serious","slug":"blog-author","avatar":"/img/photo.jpg","link":"/","description":"here is someone serious <br />只是一个小学生, 学艺不精多多见谅","socials":{"github":"https://github.com/Some1Serious","twitter":"","stackoverflow":"","wechat":"","qq":"","weibo":"","zhihu":"","csdn":"","juejin":"","customs":{"QQ":{"icon":"/svg/QQ.svg","link":"/img/myQQ.png"},"Email":{"icon":"/svg/email-fill.svg","link":"mailto:1025698918@qq.com"}}}},"mapped":true,"prev_post":{"title":"Maven-Study-day01","uid":"c2a9e80eefc355aef707e141e0e47a0d","slug":"Maven/Maven-Study-day01","date":"2022-11-11T08:41:35.000Z","updated":"2022-11-17T09:02:07.102Z","comments":true,"path":"api/articles/Maven/Maven-Study-day01.json","keywords":null,"cover":"/img/apache-maven.png","text":"学习传送门 Maven帮助我们下载管理依赖的包&lt;dependency&gt; &lt;groupId&gt;com.alibaba&lt;&#x2F;groupId&gt; &lt;artifactId&gt;druid-spring-boot-starter&lt;&#x...","link":"","photos":[],"count_time":{"symbolsCount":"1.7k","symbolsTime":"2 mins."},"categories":[{"name":"Study","slug":"Study","count":13,"path":"api/categories/Study.json"}],"tags":[{"name":"Maven","slug":"Maven","count":2,"path":"api/tags/Maven.json"}],"author":{"name":"Someone Serious","slug":"blog-author","avatar":"/img/photo.jpg","link":"/","description":"here is someone serious <br />只是一个小学生, 学艺不精多多见谅","socials":{"github":"https://github.com/Some1Serious","twitter":"","stackoverflow":"","wechat":"","qq":"","weibo":"","zhihu":"","csdn":"","juejin":"","customs":{"QQ":{"icon":"/svg/QQ.svg","link":"/img/myQQ.png"},"Email":{"icon":"/svg/email-fill.svg","link":"mailto:1025698918@qq.com"}}}},"feature":false},"next_post":{"title":"RuoYi-frame-学习-day03","uid":"307d6666c3d0b32790212432c57158e1","slug":"Ruoyi/RuoYi-frame-学习-day03","date":"2022-11-09T05:12:35.000Z","updated":"2022-11-11T08:21:54.218Z","comments":true,"path":"api/articles/Ruoyi/RuoYi-frame-学习-day03.json","keywords":null,"cover":"/img/R-C.png","text":" 特别注意 今天不想学习, 只想摆烂, 接下来我要记录一下我打的几把联盟的战绩, 计算了一下, 从我第一天搭建博客, 到现在, 从上周五(4号)到今天, 已经猛干了五天了, 顶不住了. 我们要休息! 我们要争取八小时工作制! 我莫甘娜追着豹女跑, 豹女硬顶着我的伤害把基地干爆了,...","link":"","photos":[],"count_time":{"symbolsCount":178,"symbolsTime":"1 mins."},"categories":[{"name":"Study","slug":"Study","count":13,"path":"api/categories/Study.json"}],"tags":[{"name":"RuoYi","slug":"RuoYi","count":2,"path":"api/tags/RuoYi.json"}],"author":{"name":"Someone Serious","slug":"blog-author","avatar":"/img/photo.jpg","link":"/","description":"here is someone serious <br />只是一个小学生, 学艺不精多多见谅","socials":{"github":"https://github.com/Some1Serious","twitter":"","stackoverflow":"","wechat":"","qq":"","weibo":"","zhihu":"","csdn":"","juejin":"","customs":{"QQ":{"icon":"/svg/QQ.svg","link":"/img/myQQ.png"},"Email":{"icon":"/svg/email-fill.svg","link":"mailto:1025698918@qq.com"}}}},"feature":true}}