{"name":"C","slug":"C","count":1,"postlist":[{"title":"C study day01","uid":"f8bddff16c64cf44d055f0f968e054f2","slug":"C/C-study-day01","date":"2022-11-14T14:44:27.000Z","updated":"2022-11-14T14:59:43.622Z","comments":true,"path":"api/articles/C/C-study-day01.json","keywords":null,"cover":"/img/C.jpg","text":"我觉得C语言足够难, 够我开一个档来学习, 但是我今天学C的目的是为了完成我的实验, 所以实验结束之后我估计就会搁置C一段时间. 学习传送门 留着学吧, ","link":"","photos":[],"count_time":{"symbolsCount":78,"symbolsTime":"1 mins."},"categories":[{"name":"Study","slug":"Study","count":11,"path":"api/categories/Study.json"}],"tags":[{"name":"C","slug":"C","count":1,"path":"api/tags/C.json"}],"author":{"name":"Someone Serious","slug":"blog-author","avatar":"/img/photo.jpg","link":"/","description":"here is someone serious <br />只是一个小学生, 学艺不精多多见谅","socials":{"github":"https://github.com/Some1Serious","twitter":"","stackoverflow":"","wechat":"","qq":"","weibo":"","zhihu":"","csdn":"","juejin":"","customs":{"QQ":{"icon":"/svg/QQ.svg","link":"/img/myQQ.png"},"Email":{"icon":"/svg/email-fill.svg","link":"mailto:1025698918@qq.com"}}}},"feature":true}]}