{"name":"css","slug":"css","count":1,"postlist":[{"title":"Css Skill 01","uid":"d4a56035763a2a8e516ae03b6a6591a1","slug":"HtmlCssJs/Css-Skill-01","date":"2022-11-20T03:23:42.000Z","updated":"2022-11-20T03:33:15.506Z","comments":true,"path":"api/articles/HtmlCssJs/Css-Skill-01.json","keywords":null,"cover":"/img/css.jpg","text":"刷新问题有时更改了css但是浏览器缺不更新, 原因是缓存, 我们需要ctrl + f5进行刷新就可以了. 新手指南CSS Cheat Sheet - Interactive, not a PDF | HTMLCheatSheet.com ","link":"","photos":[],"count_time":{"symbolsCount":120,"symbolsTime":"1 mins."},"categories":[{"name":"Skill","slug":"Skill","count":2,"path":"api/categories/Skill.json"}],"tags":[{"name":"css","slug":"css","count":1,"path":"api/tags/css.json"}],"author":{"name":"Someone Serious","slug":"blog-author","avatar":"/img/photo.jpg","link":"/","description":"here is someone serious <br />只是一个小学生, 学艺不精多多见谅","socials":{"github":"https://github.com/Some1Serious","twitter":"","stackoverflow":"","wechat":"","qq":"","weibo":"","zhihu":"","csdn":"","juejin":"","customs":{"QQ":{"icon":"/svg/QQ.svg","link":"/img/myQQ.png"},"Email":{"icon":"/svg/email-fill.svg","link":"mailto:1025698918@qq.com"}}}},"feature":false}]}